rst_fast_parse/_rstuvwx.py
rst_fast_parse/_vwxyz.py
rst_fast_parse/diagnostics.py
rst_fast_parse/__init__.py
rst_fast_parse/_core.py
rst_fast_parse/py.typed
rst_fast_parse/parse.py
rst_fast_parse/_abcdefg/aaaadddd.py
rst_fast_parse/_abcdefg/aaaannnn.py
rst_fast_parse/_abcdefg/aaaallll.py
rst_fast_parse/_abcdefg/aaaaffff.py
rst_fast_parse/_abcdefg/aaaammmm.py
rst_fast_parse/_abcdefg/aaaagggg.py
rst_fast_parse/_abcdefg/aaaaeeee.py
rst_fast_parse/_abcdefg/__init__.py
rst_fast_parse/_abcdefg/aaaajjjj.py
rst_fast_parse/_abcdefg/aaaabbbb.py
rst_fast_parse/_abcdefg/aaaahhhh.py
rst_fast_parse/_abcdefg/aaaacccc.py
rst_fast_parse/_abcdefg/aaaaiiii.py
rst_fast_parse/_abcdefg/aaaakkkk.py
rst_fast_parse/_abcdefg/aaaaaaaa.py
rst_fast_parse/nodes/__init__.py
rst_fast_parse/nodes/block.py
rst_fast_parse/nodes/inline.py
rst_fast_parse/cli/__init__.py
rst_fast_parse/cli/lint.py
rst_fast_parse/_opqrstu/ccccgggg.py
rst_fast_parse/_opqrstu/cccceeee.py
rst_fast_parse/_opqrstu/__init__.py
rst_fast_parse/_opqrstu/ccccdddd.py
rst_fast_parse/_opqrstu/ccccffff.py
rst_fast_parse/_opqrstu/cccciiii.py
rst_fast_parse/_opqrstu/cccccccc.py
rst_fast_parse/_opqrstu/ccccaaaa.py
rst_fast_parse/_opqrstu/cccchhhh.py
rst_fast_parse/_opqrstu/ccccbbbb.py
rst_fast_parse/_hijklmn/bbbbbbbb.py
rst_fast_parse/_hijklmn/bbbbcccc.py
rst_fast_parse/_hijklmn/bbbbaaaa.py
rst_fast_parse/_hijklmn/__init__.py
rst_fast_parse-0.0.16.dist-info/licenses/LICENSE
rst_fast_parse-0.0.16.dist-info/WHEEL
rst_fast_parse-0.0.16.dist-info/METADATA
rst_fast_parse-0.0.16.dist-info/RECORD
