Metadata-Version: 2.1
Name: rst-fast-parse
Version: 0.0.16
Summary: A fast parser for reStructuredText
Author-email: Chris Sewell <chrisj_sewell@hotmail.com>
Classifier: Development Status :: 3 - Alpha
Classifier: License :: OSI Approved :: GNU Affero General Public License v3
Classifier: Operating System :: OS Independent
Classifier: Programming Language :: Python
Classifier: Topic :: Documentation
Requires-Python: >=3.8
